Authors.rst
LICENSE.txt
MANIFEST.in
NEWS
README.md
setup.cfg
setup.py
hichipper/.DS_Store
hichipper/README.md
hichipper/__init__.py
hichipper/__init__.pyc
hichipper/cli.py
hichipper/cli.pyc
hichipper/diffloop_work.R
hichipper/hichipperHelp.py
hichipper/hichipperHelp.pyc
hichipper/hichipperProjectClass.py
hichipper/hichipperProjectClass.pyc
hichipper/hicproHelper.py
hichipper/hicproHelper.pyc
hichipper/interactionsCall.sh
hichipper/interactionsCall_inputFrags.sh
hichipper/lambdaProcess.R
hichipper/makeJSON.R
hichipper/qcReport.R
hichipper/qcReport_make.Rmd
hichipper/requirementsInstall.R
hichipper/resFragAnchorProcess.R
hichipper.egg-info/PKG-INFO
hichipper.egg-info/SOURCES.txt
hichipper.egg-info/dependency_links.txt
hichipper.egg-info/entry_points.txt
hichipper.egg-info/not-zip-safe
hichipper.egg-info/requires.txt
hichipper.egg-info/top_level.txt
tests/.DS_Store
tests/README.md
tests/__init__.py
tests/__init__.pyc
tests/test_cli.py