Metadata-Version: 1.1
Name: hichipper
Version: 0.7.7
Summary: Processing HiChIP data into loops.
Home-page: https://github.com/aryeelab/hichipper
Author: Caleb Lareau and Martin Aryee
Author-email: caleblareau@g.harvard.edu
License: MIT
Platform: any
Classifier: Development Status :: 4 - Beta
Classifier: Environment :: Console
Classifier: Intended Audience :: Developers
Classifier: License :: OSI Approved :: BSD License
Classifier: Operating System :: POSIX
Classifier: Operating System :: MacOS
Classifier: Operating System :: Unix
Classifier: Programming Language :: Python
Classifier: Programming Language :: Python :: 2
Classifier: Topic :: Software Development :: Libraries :: Python Modules
